concord4ws/__init__.py
concord4ws/client.py
concord4ws/types.py
concord4ws-0.3.1.dist-info/LICENSE
concord4ws-0.3.1.dist-info/METADATA
concord4ws-0.3.1.dist-info/WHEEL
concord4ws-0.3.1.dist-info/RECORD
