Metadata-Version: 2.3
Name: concord4ws
Version: 0.3.1
Summary: A package for interacting with the concord4ws server.
Author: Joey Eamigh
Author-email: 55670930+JoeyEamigh@users.noreply.github.com
Requires-Python: >=3.11,<4.0
Classifier: License :: OSI Approved :: MIT License
Classifier: Operating System :: OS Independent
Classifier: Programming Language :: Python :: 3
Classifier: Programming Language :: Python :: 3.11
Classifier: Programming Language :: Python :: 3.12
Classifier: Programming Language :: Python :: 3.13
Requires-Dist: pydantic (>=2.10.0,<3.0.0)
Requires-Dist: websockets (>=14.0,<15.0)
Project-URL: Bug Tracker, https://github.com/JoeyEamigh/concord4ws-py/issues
Project-URL: Homepage, https://github.com/JoeyEamigh/concord4ws-py
